jupyter_ai_chat_commands/__init__.py
jupyter_ai_chat_commands/_version.py
jupyter_ai_chat_commands/extension_app.py
jupyter_ai_chat_commands/handlers.py
jupyter_ai_chat_commands/tests/__init__.py
jupyter_ai_chat_commands/tests/test_handlers.py
jupyter_ai_chat_commands-0.0.4.data/data/etc/jupyter/jupyter_server_config.d/jupyter_ai_chat_commands.json
jupyter_ai_chat_commands-0.0.4.data/data/share/jupyter/labextensions/@jupyter-ai/chat-commands/package.json
jupyter_ai_chat_commands-0.0.4.data/data/share/jupyter/labextensions/@jupyter-ai/chat-commands/static/505.b674246ea36d3bd7e7b4.js
jupyter_ai_chat_commands-0.0.4.data/data/share/jupyter/labextensions/@jupyter-ai/chat-commands/static/505.b674246ea36d3bd7e7b4.js.LICENSE.txt
jupyter_ai_chat_commands-0.0.4.data/data/share/jupyter/labextensions/@jupyter-ai/chat-commands/static/728.b813fd4a9d73f3334509.js
jupyter_ai_chat_commands-0.0.4.data/data/share/jupyter/labextensions/@jupyter-ai/chat-commands/static/996.97902422a9604e25c13e.js
jupyter_ai_chat_commands-0.0.4.data/data/share/jupyter/labextensions/@jupyter-ai/chat-commands/static/remoteEntry.d6dcb45964a9e2b0fb60.js
jupyter_ai_chat_commands-0.0.4.data/data/share/jupyter/labextensions/@jupyter-ai/chat-commands/static/style.js
jupyter_ai_chat_commands-0.0.4.data/data/share/jupyter/labextensions/@jupyter-ai/chat-commands/static/third-party-licenses.json
jupyter_ai_chat_commands-0.0.4.data/data/share/jupyter/labextensions/@jupyter-ai/chat-commands/install.json
jupyter_ai_chat_commands-0.0.4.dist-info/METADATA
jupyter_ai_chat_commands-0.0.4.dist-info/WHEEL
jupyter_ai_chat_commands-0.0.4.dist-info/licenses/LICENSE
jupyter_ai_chat_commands-0.0.4.dist-info/RECORD
